test_image_results/__init__.py
test_image_results/client.py
test_image_results-0.0.3.dist-info/DESCRIPTION.rst
test_image_results-0.0.3.dist-info/METADATA
test_image_results-0.0.3.dist-info/RECORD
test_image_results-0.0.3.dist-info/WHEEL
test_image_results-0.0.3.dist-info/metadata.json
test_image_results-0.0.3.dist-info/top_level.txt
